drf_discord_handler/__init__.py
drf_discord_handler/clients/__init__.py
drf_discord_handler/clients/discord_client.py
drf_discord_handler/handlers/__init__.py
drf_discord_handler/handlers/exception_handler.py
drf_discord_handler/settings/__init__.py
drf_discord_handler/settings/config.py
drf_discord_handler/utils/__init__.py
drf_discord_handler/utils/filters.py
drf_discord_handler/utils/formatters.py
drf_discord_handler-0.1.3.dist-info/licenses/LICENSE
drf_discord_handler-0.1.3.dist-info/METADATA
drf_discord_handler-0.1.3.dist-info/WHEEL
drf_discord_handler-0.1.3.dist-info/top_level.txt
drf_discord_handler-0.1.3.dist-info/RECORD
