Metadata-Version: 2.4
Name: drf-discord-handler
Version: 0.1.3
Summary: Add your description here
Author-email: shinkeonkim <dev.shinkeonkim@gmail.com>
License: MIT
Project-URL: Homepage, https://github.com/shinkeonkim/drf_discord_handler
Project-URL: Repository, https://github.com/shinkeonkim/drf_discord_handler
Classifier: Programming Language :: Python :: 3
Classifier: Programming Language :: Python :: 3.14
Requires-Python: >=3.14
License-File: LICENSE
Requires-Dist: django>=6.0
Requires-Dist: djangorestframework>=3.16.1
Dynamic: license-file
